{
  "NIO": {
    "drawdown_percent": 11.68,
    "days_since_ath": 16
  },
  "HTG": {
    "drawdown_percent": 11.82,
    "days_since_ath": 16
  },
  "THB": {
    "drawdown_percent": 11.1,
    "days_since_ath": 16
  },
  "LAK": {
    "drawdown_percent": 11.68,
    "days_since_ath": 16
  },
  "CRC": {
    "drawdown_percent": 11.97,
    "days_since_ath": 16
  },
  "BYN": {
    "drawdown_percent": 14.52,
    "days_since_ath": 15
  },
  "CAD": {
    "drawdown_percent": 11.26,
    "days_since_ath": 16
  },
  "ILS": {
    "drawdown_percent": 13.22,
    "days_since_ath": 71
  },
  "KHR": {
    "drawdown_percent": 11.73,
    "days_since_ath": 16
  },
  "HNL": {
    "drawdown_percent": 11.71,
    "days_since_ath": 16
  },
  "CVE": {
    "drawdown_percent": 11.1,
    "days_since_ath": 16
  },
  "PGK": {
    "drawdown_percent": 11.59,
    "days_since_ath": 16
  },
  "GNF": {
    "drawdown_percent": 11.66,
    "days_since_ath": 16
  },
  "GMD": {
    "drawdown_percent": 11.73,
    "days_since_ath": 16
  },
  "RUB": {
    "drawdown_percent": 21.44,
    "days_since_ath": 307
  },
  "JOD": {
    "drawdown_percent": 11.79,
    "days_since_ath": 16
  },
  "BRL": {
    "drawdown_percent": 12.4,
    "days_since_ath": 99
  },
  "MYR": {
    "drawdown_percent": 11.39,
    "days_since_ath": 16
  },
  "PYG": {
    "drawdown_percent": 18.39,
    "days_since_ath": 99
  },
  "KES": {
    "drawdown_percent": 11.74,
    "days_since_ath": 16
  },
  "LKR": {
    "drawdown_percent": 11.72,
    "days_since_ath": 16
  },
  "BIF": {
    "drawdown_percent": 12.06,
    "days_since_ath": 16
  },
  "CZK": {
    "drawdown_percent": 14.32,
    "days_since_ath": 273
  },
  "KZT": {
    "drawdown_percent": 13.26,
    "days_since_ath": 16
  },
  "AED": {
    "drawdown_percent": 11.79,
    "days_since_ath": 16
  },
  "AWG": {
    "drawdown_percent": 11.79,
    "days_since_ath": 16
  },
  "ARS": {
    "drawdown_percent": 9.44,
    "days_since_ath": 16
  },
  "TND": {
    "drawdown_percent": 11.13,
    "days_since_ath": 16
  },
  "EUR": {
    "drawdown_percent": 11.1,
    "days_since_ath": 16
  },
  "ISK": {
    "drawdown_percent": 12.86,
    "days_since_ath": 273
  },
  "YER": {
    "drawdown_percent": 11.91,
    "days_since_ath": 16
  },
  "SZL": {
    "drawdown_percent": 13.22,
    "days_since_ath": 99
  },
  "TRY": {
    "drawdown_percent": 11.26,
    "days_since_ath": 16
  },
  "SAR": {
    "drawdown_percent": 11.79,
    "days_since_ath": 16
  },
  "LSL": {
    "drawdown_percent": 13.22,
    "days_since_ath": 99
  },
  "JPY": {
    "drawdown_percent": 10.85,
    "days_since_ath": 12
  },
  "LRD": {
    "drawdown_percent": 17.58,
    "days_since_ath": 71
  },
  "SEK": {
    "drawdown_percent": 14.93,
    "days_since_ath": 273
  },
  "FJD": {
    "drawdown_percent": 10.73,
    "days_since_ath": 16
  },
  "KMF": {
    "drawdown_percent": 11.1,
    "days_since_ath": 16
  },
  "KYD": {
    "drawdown_percent": 11.79,
    "days_since_ath": 16
  },
  "RSD": {
    "drawdown_percent": 11.13,
    "days_since_ath": 16
  },
  "UYU": {
    "drawdown_percent": 11.36,
    "days_since_ath": 16
  },
  "HUF": {
    "drawdown_percent": 15.98,
    "days_since_ath": 273
  },
  "DZD": {
    "drawdown_percent": 11.77,
    "days_since_ath": 16
  },
  "BHD": {
    "drawdown_percent": 11.79,
    "days_since_ath": 16
  },
  "MAD": {
    "drawdown_percent": 10.83,
    "days_since_ath": 16
  },
  "NPR": {
    "drawdown_percent": 12.65,
    "days_since_ath": 16
  },
  "DKK": {
    "drawdown_percent": 11.08,
    "days_since_ath": 16
  },
  "ALL": {
    "drawdown_percent": 11.24,
    "days_since_ath": 16
  },
  "TTD": {
    "drawdown_percent": 11.48,
    "days_since_ath": 16
  },
  "MXN": {
    "drawdown_percent": 11.8,
    "days_since_ath": 16
  },
  "BND": {
    "drawdown_percent": 11.45,
    "days_since_ath": 16
  },
  "SCR": {
    "drawdown_percent": 12.9,
    "days_since_ath": 16
  },
  "XPF": {
    "drawdown_percent": 11.1,
    "days_since_ath": 16
  },
  "KRW": {
    "drawdown_percent": 10.83,
    "days_since_ath": 16
  },
  "AFN": {
    "drawdown_percent": 13.24,
    "days_since_ath": 99
  },
  "IRR": {
    "drawdown_percent": 12.53,
    "days_since_ath": 15
  },
  "OMR": {
    "drawdown_percent": 11.79,
    "days_since_ath": 16
  },
  "SOS": {
    "drawdown_percent": 11.86,
    "days_since_ath": 16
  },
  "GBP": {
    "drawdown_percent": 11.37,
    "days_since_ath": 16
  },
  "CDF": {
    "drawdown_percent": 31.49,
    "days_since_ath": 99
  },
  "PHP": {
    "drawdown_percent": 11.5,
    "days_since_ath": 16
  },
  "NGN": {
    "drawdown_percent": 13.75,
    "days_since_ath": 68
  },
  "NOK": {
    "drawdown_percent": 11.75,
    "days_since_ath": 71
  },
  "CLP": {
    "drawdown_percent": 12.15,
    "days_since_ath": 16
  },
  "USD": {
    "drawdown_percent": 11.79,
    "days_since_ath": 16
  },
  "BSD": {
    "drawdown_percent": 11.79,
    "days_since_ath": 16
  },
  "VES": {
    "drawdown_percent": 2.65,
    "days_since_ath": 11
  },
  "XAF": {
    "drawdown_percent": 11.1,
    "days_since_ath": 16
  },
  "LBP": {
    "drawdown_percent": 11.79,
    "days_since_ath": 16
  },
  "CUP": {
    "drawdown_percent": 11.79,
    "days_since_ath": 16
  },
  "DOP": {
    "drawdown_percent": 10.36,
    "days_since_ath": 16
  },
  "PAB": {
    "drawdown_percent": 11.79,
    "days_since_ath": 16
  },
  "MUR": {
    "drawdown_percent": 12.66,
    "days_since_ath": 16
  },
  "HKD": {
    "drawdown_percent": 11.94,
    "days_since_ath": 16
  },
  "LYD": {
    "drawdown_percent": 11.44,
    "days_since_ath": 16
  },
  "QAR": {
    "drawdown_percent": 11.79,
    "days_since_ath": 16
  },
  "VND": {
    "drawdown_percent": 11.97,
    "days_since_ath": 16
  },
  "DJF": {
    "drawdown_percent": 11.79,
    "days_since_ath": 16
  },
  "SDG": {
    "drawdown_percent": 24.69,
    "days_since_ath": 68
  },
  "MWK": {
    "drawdown_percent": 11.83,
    "days_since_ath": 16
  },
  "TWD": {
    "drawdown_percent": 11.3,
    "days_since_ath": 16
  },
  "MOP": {
    "drawdown_percent": 11.94,
    "days_since_ath": 16
  },
  "NZD": {
    "drawdown_percent": 10.41,
    "days_since_ath": 16
  },
  "NAD": {
    "drawdown_percent": 13.22,
    "days_since_ath": 99
  },
  "PEN": {
    "drawdown_percent": 14.22,
    "days_since_ath": 99
  },
  "ETB": {
    "drawdown_percent": 9.4,
    "days_since_ath": 15
  },
  "BBD": {
    "drawdown_percent": 11.79,
    "days_since_ath": 16
  },
  "BOB": {
    "drawdown_percent": 11.8,
    "days_since_ath": 16
  },
  "PKR": {
    "drawdown_percent": 11.76,
    "days_since_ath": 16
  },
  "KWD": {
    "drawdown_percent": 11.72,
    "days_since_ath": 16
  },
  "EGP": {
    "drawdown_percent": 13.42,
    "days_since_ath": 99
  },
  "JMD": {
    "drawdown_percent": 11.43,
    "days_since_ath": 16
  },
  "XOF": {
    "drawdown_percent": 11.1,
    "days_since_ath": 16
  },
  "BGN": {
    "drawdown_percent": 11.11,
    "days_since_ath": 16
  },
  "CNY": {
    "drawdown_percent": 12.18,
    "days_since_ath": 16
  },
  "COP": {
    "drawdown_percent": 14.68,
    "days_since_ath": 71
  },
  "IDR": {
    "drawdown_percent": 11.88,
    "days_since_ath": 16
  },
  "MGA": {
    "drawdown_percent": 10.83,
    "days_since_ath": 16
  },
  "XCD": {
    "drawdown_percent": 11.79,
    "days_since_ath": 16
  },
  "MMK": {
    "drawdown_percent": 34.25,
    "days_since_ath": 273
  },
  "TMT": {
    "drawdown_percent": 11.8,
    "days_since_ath": 16
  },
  "RWF": {
    "drawdown_percent": 10.49,
    "days_since_ath": 16
  },
  "GYD": {
    "drawdown_percent": 11.83,
    "days_since_ath": 16
  },
  "BWP": {
    "drawdown_percent": 13.6,
    "days_since_ath": 16
  },
  "BDT": {
    "drawdown_percent": 11.61,
    "days_since_ath": 16
  },
  "TZS": {
    "drawdown_percent": 15.08,
    "days_since_ath": 99
  },
  "ZAR": {
    "drawdown_percent": 13.23,
    "days_since_ath": 99
  },
  "MKD": {
    "drawdown_percent": 11.34,
    "days_since_ath": 16
  },
  "AUD": {
    "drawdown_percent": 10.5,
    "days_since_ath": 16
  },
  "RON": {
    "drawdown_percent": 11.23,
    "days_since_ath": 16
  },
  "PLN": {
    "drawdown_percent": 11.48,
    "days_since_ath": 16
  },
  "BZD": {
    "drawdown_percent": 11.79,
    "days_since_ath": 16
  },
  "MVR": {
    "drawdown_percent": 11.85,
    "days_since_ath": 16
  },
  "UGX": {
    "drawdown_percent": 12.25,
    "days_since_ath": 99
  },
  "IQD": {
    "drawdown_percent": 11.75,
    "days_since_ath": 16
  },
  "UZS": {
    "drawdown_percent": 13.97,
    "days_since_ath": 99
  },
  "BMD": {
    "drawdown_percent": 11.79,
    "days_since_ath": 16
  },
  "ANG": {
    "drawdown_percent": 11.79,
    "days_since_ath": 16
  },
  "UAH": {
    "drawdown_percent": 10.67,
    "days_since_ath": 16
  },
  "ZMW": {
    "drawdown_percent": 17.72,
    "days_since_ath": 273
  },
  "INR": {
    "drawdown_percent": 12.65,
    "days_since_ath": 16
  },
  "SGD": {
    "drawdown_percent": 11.45,
    "days_since_ath": 16
  },
  "CHF": {
    "drawdown_percent": 12.52,
    "days_since_ath": 273
  },
  "MRU": {
    "drawdown_percent": 11.54,
    "days_since_ath": 16
  },
  "MZN": {
    "drawdown_percent": 11.89,
    "days_since_ath": 16
  },
  "GTQ": {
    "drawdown_percent": 11.79,
    "days_since_ath": 16
  },
  "GHS": {
    "drawdown_percent": 27.57,
    "days_since_ath": 273
  },
  "MDL": {
    "drawdown_percent": 10.86,
    "days_since_ath": 16
  }
}