{
  "NIO": {
    "drawdown_percent": 48.02,
    "days_since_ath": 256
  },
  "HTG": {
    "drawdown_percent": 48.24,
    "days_since_ath": 256
  },
  "THB": {
    "drawdown_percent": 47.86,
    "days_since_ath": 256
  },
  "LAK": {
    "drawdown_percent": 47.39,
    "days_since_ath": 256
  },
  "CRC": {
    "drawdown_percent": 53.05,
    "days_since_ath": 256
  },
  "BYN": {
    "drawdown_percent": 56.98,
    "days_since_ath": 255
  },
  "CAD": {
    "drawdown_percent": 47.93,
    "days_since_ath": 256
  },
  "ILS": {
    "drawdown_percent": 54.72,
    "days_since_ath": 311
  },
  "KHR": {
    "drawdown_percent": 47.77,
    "days_since_ath": 256
  },
  "HNL": {
    "drawdown_percent": 47.08,
    "days_since_ath": 256
  },
  "CVE": {
    "drawdown_percent": 47.49,
    "days_since_ath": 256
  },
  "PGK": {
    "drawdown_percent": 46.38,
    "days_since_ath": 256
  },
  "GNF": {
    "drawdown_percent": 47.6,
    "days_since_ath": 256
  },
  "GMD": {
    "drawdown_percent": 47.53,
    "days_since_ath": 256
  },
  "RUB": {
    "drawdown_percent": 58.58,
    "days_since_ath": 547
  },
  "JOD": {
    "drawdown_percent": 48.08,
    "days_since_ath": 256
  },
  "BRL": {
    "drawdown_percent": 51.63,
    "days_since_ath": 339
  },
  "MYR": {
    "drawdown_percent": 49.82,
    "days_since_ath": 256
  },
  "PYG": {
    "drawdown_percent": 58.37,
    "days_since_ath": 339
  },
  "KES": {
    "drawdown_percent": 48.01,
    "days_since_ath": 256
  },
  "LKR": {
    "drawdown_percent": 42.81,
    "days_since_ath": 256
  },
  "BIF": {
    "drawdown_percent": 47.5,
    "days_since_ath": 256
  },
  "CZK": {
    "drawdown_percent": 49.68,
    "days_since_ath": 513
  },
  "KZT": {
    "drawdown_percent": 53.74,
    "days_since_ath": 256
  },
  "AED": {
    "drawdown_percent": 48.08,
    "days_since_ath": 256
  },
  "AWG": {
    "drawdown_percent": 48.08,
    "days_since_ath": 256
  },
  "ARS": {
    "drawdown_percent": 47.79,
    "days_since_ath": 256
  },
  "TND": {
    "drawdown_percent": 47.85,
    "days_since_ath": 256
  },
  "EUR": {
    "drawdown_percent": 47.49,
    "days_since_ath": 256
  },
  "ISK": {
    "drawdown_percent": 47.48,
    "days_since_ath": 513
  },
  "YER": {
    "drawdown_percent": 48.18,
    "days_since_ath": 256
  },
  "SZL": {
    "drawdown_percent": 52.07,
    "days_since_ath": 339
  },
  "TRY": {
    "drawdown_percent": 42.29,
    "days_since_ath": 256
  },
  "SAR": {
    "drawdown_percent": 48.08,
    "days_since_ath": 256
  },
  "LSL": {
    "drawdown_percent": 52.07,
    "days_since_ath": 339
  },
  "JPY": {
    "drawdown_percent": 44.16,
    "days_since_ath": 252
  },
  "LRD": {
    "drawdown_percent": 51.75,
    "days_since_ath": 311
  },
  "SEK": {
    "drawdown_percent": 50.2,
    "days_since_ath": 513
  },
  "FJD": {
    "drawdown_percent": 49.16,
    "days_since_ath": 256
  },
  "KMF": {
    "drawdown_percent": 47.49,
    "days_since_ath": 256
  },
  "KYD": {
    "drawdown_percent": 48.08,
    "days_since_ath": 256
  },
  "RSD": {
    "drawdown_percent": 47.37,
    "days_since_ath": 256
  },
  "UYU": {
    "drawdown_percent": 47.08,
    "days_since_ath": 256
  },
  "HUF": {
    "drawdown_percent": 55.43,
    "days_since_ath": 513
  },
  "DZD": {
    "drawdown_percent": 46.67,
    "days_since_ath": 256
  },
  "BHD": {
    "drawdown_percent": 48.08,
    "days_since_ath": 256
  },
  "MAD": {
    "drawdown_percent": 47.33,
    "days_since_ath": 256
  },
  "NPR": {
    "drawdown_percent": 44.67,
    "days_since_ath": 256
  },
  "DKK": {
    "drawdown_percent": 47.47,
    "days_since_ath": 256
  },
  "ALL": {
    "drawdown_percent": 48.43,
    "days_since_ath": 256
  },
  "TTD": {
    "drawdown_percent": 47.99,
    "days_since_ath": 256
  },
  "MXN": {
    "drawdown_percent": 51.44,
    "days_since_ath": 256
  },
  "BND": {
    "drawdown_percent": 48.36,
    "days_since_ath": 256
  },
  "SCR": {
    "drawdown_percent": 50.87,
    "days_since_ath": 256
  },
  "XPF": {
    "drawdown_percent": 47.49,
    "days_since_ath": 256
  },
  "KRW": {
    "drawdown_percent": 44.27,
    "days_since_ath": 256
  },
  "AFN": {
    "drawdown_percent": 51.28,
    "days_since_ath": 339
  },
  "IRR": {
    "drawdown_percent": 19.69,
    "days_since_ath": 40
  },
  "OMR": {
    "drawdown_percent": 48.08,
    "days_since_ath": 256
  },
  "SOS": {
    "drawdown_percent": 48.12,
    "days_since_ath": 256
  },
  "GBP": {
    "drawdown_percent": 47.89,
    "days_since_ath": 256
  },
  "CDF": {
    "drawdown_percent": 58.24,
    "days_since_ath": 339
  },
  "PHP": {
    "drawdown_percent": 46.01,
    "days_since_ath": 256
  },
  "NGN": {
    "drawdown_percent": 52.97,
    "days_since_ath": 308
  },
  "NOK": {
    "drawdown_percent": 50.95,
    "days_since_ath": 311
  },
  "CLP": {
    "drawdown_percent": 51.86,
    "days_since_ath": 256
  },
  "USD": {
    "drawdown_percent": 48.08,
    "days_since_ath": 256
  },
  "BSD": {
    "drawdown_percent": 48.08,
    "days_since_ath": 256
  },
  "VES": {
    "drawdown_percent": 5.98,
    "days_since_ath": 23
  },
  "XAF": {
    "drawdown_percent": 47.49,
    "days_since_ath": 256
  },
  "LBP": {
    "drawdown_percent": 48.08,
    "days_since_ath": 256
  },
  "CUP": {
    "drawdown_percent": 48.08,
    "days_since_ath": 256
  },
  "DOP": {
    "drawdown_percent": 51.27,
    "days_since_ath": 256
  },
  "PAB": {
    "drawdown_percent": 48.08,
    "days_since_ath": 256
  },
  "MUR": {
    "drawdown_percent": 46.04,
    "days_since_ath": 256
  },
  "HKD": {
    "drawdown_percent": 47.74,
    "days_since_ath": 256
  },
  "LYD": {
    "drawdown_percent": 38.81,
    "days_since_ath": 256
  },
  "QAR": {
    "drawdown_percent": 48.08,
    "days_since_ath": 256
  },
  "VND": {
    "drawdown_percent": 48.3,
    "days_since_ath": 256
  },
  "DJF": {
    "drawdown_percent": 48.08,
    "days_since_ath": 256
  },
  "SDG": {
    "drawdown_percent": 55.87,
    "days_since_ath": 308
  },
  "MWK": {
    "drawdown_percent": 48.03,
    "days_since_ath": 256
  },
  "TWD": {
    "drawdown_percent": 46.13,
    "days_since_ath": 256
  },
  "MOP": {
    "drawdown_percent": 47.74,
    "days_since_ath": 256
  },
  "NZD": {
    "drawdown_percent": 48.08,
    "days_since_ath": 256
  },
  "NAD": {
    "drawdown_percent": 52.07,
    "days_since_ath": 339
  },
  "PEN": {
    "drawdown_percent": 49.33,
    "days_since_ath": 339
  },
  "ETB": {
    "drawdown_percent": 42.99,
    "days_since_ath": 255
  },
  "BBD": {
    "drawdown_percent": 48.08,
    "days_since_ath": 256
  },
  "BOB": {
    "drawdown_percent": 48.11,
    "days_since_ath": 256
  },
  "PKR": {
    "drawdown_percent": 48.96,
    "days_since_ath": 256
  },
  "KWD": {
    "drawdown_percent": 47.63,
    "days_since_ath": 256
  },
  "EGP": {
    "drawdown_percent": 46.14,
    "days_since_ath": 339
  },
  "JMD": {
    "drawdown_percent": 48.74,
    "days_since_ath": 256
  },
  "XOF": {
    "drawdown_percent": 47.49,
    "days_since_ath": 256
  },
  "BGN": {
    "drawdown_percent": 47.49,
    "days_since_ath": 256
  },
  "CNY": {
    "drawdown_percent": 50.69,
    "days_since_ath": 256
  },
  "COP": {
    "drawdown_percent": 54.27,
    "days_since_ath": 311
  },
  "IDR": {
    "drawdown_percent": 44.47,
    "days_since_ath": 256
  },
  "MGA": {
    "drawdown_percent": 51.1,
    "days_since_ath": 256
  },
  "XCD": {
    "drawdown_percent": 48.08,
    "days_since_ath": 256
  },
  "MMK": {
    "drawdown_percent": 61.29,
    "days_since_ath": 513
  },
  "TMT": {
    "drawdown_percent": 48.09,
    "days_since_ath": 256
  },
  "RWF": {
    "drawdown_percent": 47.46,
    "days_since_ath": 256
  },
  "GYD": {
    "drawdown_percent": 48.1,
    "days_since_ath": 256
  },
  "BWP": {
    "drawdown_percent": 49.66,
    "days_since_ath": 256
  },
  "BDT": {
    "drawdown_percent": 47.6,
    "days_since_ath": 256
  },
  "TZS": {
    "drawdown_percent": 46.63,
    "days_since_ath": 339
  },
  "ZAR": {
    "drawdown_percent": 52.08,
    "days_since_ath": 339
  },
  "MKD": {
    "drawdown_percent": 47.56,
    "days_since_ath": 256
  },
  "AUD": {
    "drawdown_percent": 51.5,
    "days_since_ath": 256
  },
  "RON": {
    "drawdown_percent": 46.03,
    "days_since_ath": 256
  },
  "PLN": {
    "drawdown_percent": 47.7,
    "days_since_ath": 256
  },
  "BZD": {
    "drawdown_percent": 48.08,
    "days_since_ath": 256
  },
  "MVR": {
    "drawdown_percent": 47.99,
    "days_since_ath": 256
  },
  "UGX": {
    "drawdown_percent": 45.46,
    "days_since_ath": 339
  },
  "IQD": {
    "drawdown_percent": 48.0,
    "days_since_ath": 256
  },
  "UZS": {
    "drawdown_percent": 49.91,
    "days_since_ath": 339
  },
  "BMD": {
    "drawdown_percent": 48.08,
    "days_since_ath": 256
  },
  "ANG": {
    "drawdown_percent": 48.08,
    "days_since_ath": 256
  },
  "UAH": {
    "drawdown_percent": 43.6,
    "days_since_ath": 256
  },
  "ZMW": {
    "drawdown_percent": 62.29,
    "days_since_ath": 513
  },
  "INR": {
    "drawdown_percent": 44.67,
    "days_since_ath": 256
  },
  "SGD": {
    "drawdown_percent": 48.36,
    "days_since_ath": 256
  },
  "CHF": {
    "drawdown_percent": 48.44,
    "days_since_ath": 513
  },
  "MRU": {
    "drawdown_percent": 48.06,
    "days_since_ath": 256
  },
  "MZN": {
    "drawdown_percent": 48.24,
    "days_since_ath": 256
  },
  "GTQ": {
    "drawdown_percent": 48.31,
    "days_since_ath": 256
  },
  "GHS": {
    "drawdown_percent": 56.01,
    "days_since_ath": 513
  },
  "MDL": {
    "drawdown_percent": 45.84,
    "days_since_ath": 256
  }
}