{
  "NIO": {
    "drawdown_percent": 37.31,
    "days_since_ath": 210
  },
  "HTG": {
    "drawdown_percent": 37.58,
    "days_since_ath": 210
  },
  "THB": {
    "drawdown_percent": 37.26,
    "days_since_ath": 210
  },
  "LAK": {
    "drawdown_percent": 36.81,
    "days_since_ath": 210
  },
  "CRC": {
    "drawdown_percent": 43.45,
    "days_since_ath": 210
  },
  "BYN": {
    "drawdown_percent": 47.19,
    "days_since_ath": 209
  },
  "CAD": {
    "drawdown_percent": 39.07,
    "days_since_ath": 210
  },
  "ILS": {
    "drawdown_percent": 44.89,
    "days_since_ath": 265
  },
  "KHR": {
    "drawdown_percent": 37.77,
    "days_since_ath": 210
  },
  "HNL": {
    "drawdown_percent": 36.5,
    "days_since_ath": 210
  },
  "CVE": {
    "drawdown_percent": 37.36,
    "days_since_ath": 210
  },
  "PGK": {
    "drawdown_percent": 35.75,
    "days_since_ath": 210
  },
  "GNF": {
    "drawdown_percent": 36.8,
    "days_since_ath": 210
  },
  "GMD": {
    "drawdown_percent": 36.81,
    "days_since_ath": 210
  },
  "RUB": {
    "drawdown_percent": 48.32,
    "days_since_ath": 501
  },
  "JOD": {
    "drawdown_percent": 37.45,
    "days_since_ath": 210
  },
  "BRL": {
    "drawdown_percent": 42.77,
    "days_since_ath": 293
  },
  "MYR": {
    "drawdown_percent": 40.97,
    "days_since_ath": 210
  },
  "PYG": {
    "drawdown_percent": 49.1,
    "days_since_ath": 293
  },
  "KES": {
    "drawdown_percent": 37.48,
    "days_since_ath": 210
  },
  "LKR": {
    "drawdown_percent": 33.94,
    "days_since_ath": 210
  },
  "BIF": {
    "drawdown_percent": 36.92,
    "days_since_ath": 210
  },
  "CZK": {
    "drawdown_percent": 39.33,
    "days_since_ath": 467
  },
  "KZT": {
    "drawdown_percent": 47.04,
    "days_since_ath": 210
  },
  "AED": {
    "drawdown_percent": 37.45,
    "days_since_ath": 210
  },
  "AWG": {
    "drawdown_percent": 37.45,
    "days_since_ath": 210
  },
  "ARS": {
    "drawdown_percent": 39.36,
    "days_since_ath": 210
  },
  "TND": {
    "drawdown_percent": 37.85,
    "days_since_ath": 210
  },
  "EUR": {
    "drawdown_percent": 37.37,
    "days_since_ath": 210
  },
  "ISK": {
    "drawdown_percent": 37.55,
    "days_since_ath": 467
  },
  "YER": {
    "drawdown_percent": 37.49,
    "days_since_ath": 210
  },
  "SZL": {
    "drawdown_percent": 40.59,
    "days_since_ath": 293
  },
  "TRY": {
    "drawdown_percent": 32.26,
    "days_since_ath": 210
  },
  "SAR": {
    "drawdown_percent": 37.45,
    "days_since_ath": 210
  },
  "LSL": {
    "drawdown_percent": 40.59,
    "days_since_ath": 293
  },
  "JPY": {
    "drawdown_percent": 34.1,
    "days_since_ath": 206
  },
  "LRD": {
    "drawdown_percent": 41.33,
    "days_since_ath": 265
  },
  "SEK": {
    "drawdown_percent": 40.89,
    "days_since_ath": 467
  },
  "FJD": {
    "drawdown_percent": 38.91,
    "days_since_ath": 210
  },
  "KMF": {
    "drawdown_percent": 37.36,
    "days_since_ath": 210
  },
  "KYD": {
    "drawdown_percent": 37.45,
    "days_since_ath": 210
  },
  "RSD": {
    "drawdown_percent": 37.22,
    "days_since_ath": 210
  },
  "UYU": {
    "drawdown_percent": 37.33,
    "days_since_ath": 210
  },
  "HUF": {
    "drawdown_percent": 44.53,
    "days_since_ath": 467
  },
  "DZD": {
    "drawdown_percent": 35.91,
    "days_since_ath": 210
  },
  "BHD": {
    "drawdown_percent": 37.45,
    "days_since_ath": 210
  },
  "MAD": {
    "drawdown_percent": 36.52,
    "days_since_ath": 210
  },
  "NPR": {
    "drawdown_percent": 33.07,
    "days_since_ath": 210
  },
  "DKK": {
    "drawdown_percent": 37.37,
    "days_since_ath": 210
  },
  "ALL": {
    "drawdown_percent": 37.78,
    "days_since_ath": 210
  },
  "TTD": {
    "drawdown_percent": 37.45,
    "days_since_ath": 210
  },
  "MXN": {
    "drawdown_percent": 40.52,
    "days_since_ath": 210
  },
  "BND": {
    "drawdown_percent": 38.23,
    "days_since_ath": 210
  },
  "SCR": {
    "drawdown_percent": 41.63,
    "days_since_ath": 210
  },
  "XPF": {
    "drawdown_percent": 37.36,
    "days_since_ath": 210
  },
  "KRW": {
    "drawdown_percent": 34.4,
    "days_since_ath": 210
  },
  "AFN": {
    "drawdown_percent": 40.52,
    "days_since_ath": 293
  },
  "IRR": {
    "drawdown_percent": 8.54,
    "days_since_ath": 1
  },
  "OMR": {
    "drawdown_percent": 37.45,
    "days_since_ath": 210
  },
  "SOS": {
    "drawdown_percent": 37.52,
    "days_since_ath": 210
  },
  "GBP": {
    "drawdown_percent": 37.88,
    "days_since_ath": 210
  },
  "CDF": {
    "drawdown_percent": 49.03,
    "days_since_ath": 293
  },
  "PHP": {
    "drawdown_percent": 33.74,
    "days_since_ath": 210
  },
  "NGN": {
    "drawdown_percent": 42.57,
    "days_since_ath": 262
  },
  "NOK": {
    "drawdown_percent": 42.18,
    "days_since_ath": 265
  },
  "CLP": {
    "drawdown_percent": 40.96,
    "days_since_ath": 210
  },
  "USD": {
    "drawdown_percent": 37.45,
    "days_since_ath": 210
  },
  "BSD": {
    "drawdown_percent": 37.45,
    "days_since_ath": 210
  },
  "VES": {
    "drawdown_percent": 0.09,
    "days_since_ath": 1
  },
  "XAF": {
    "drawdown_percent": 37.36,
    "days_since_ath": 210
  },
  "LBP": {
    "drawdown_percent": 37.45,
    "days_since_ath": 210
  },
  "CUP": {
    "drawdown_percent": 37.45,
    "days_since_ath": 210
  },
  "DOP": {
    "drawdown_percent": 40.35,
    "days_since_ath": 210
  },
  "PAB": {
    "drawdown_percent": 37.45,
    "days_since_ath": 210
  },
  "MUR": {
    "drawdown_percent": 35.47,
    "days_since_ath": 210
  },
  "HKD": {
    "drawdown_percent": 37.02,
    "days_since_ath": 210
  },
  "LYD": {
    "drawdown_percent": 26.59,
    "days_since_ath": 210
  },
  "QAR": {
    "drawdown_percent": 37.45,
    "days_since_ath": 210
  },
  "VND": {
    "drawdown_percent": 37.45,
    "days_since_ath": 210
  },
  "DJF": {
    "drawdown_percent": 37.45,
    "days_since_ath": 210
  },
  "SDG": {
    "drawdown_percent": 40.11,
    "days_since_ath": 262
  },
  "MWK": {
    "drawdown_percent": 37.46,
    "days_since_ath": 210
  },
  "TWD": {
    "drawdown_percent": 34.95,
    "days_since_ath": 210
  },
  "MOP": {
    "drawdown_percent": 37.02,
    "days_since_ath": 210
  },
  "NZD": {
    "drawdown_percent": 38.13,
    "days_since_ath": 210
  },
  "NAD": {
    "drawdown_percent": 40.59,
    "days_since_ath": 293
  },
  "PEN": {
    "drawdown_percent": 36.75,
    "days_since_ath": 293
  },
  "ETB": {
    "drawdown_percent": 32.29,
    "days_since_ath": 209
  },
  "BBD": {
    "drawdown_percent": 37.45,
    "days_since_ath": 210
  },
  "BOB": {
    "drawdown_percent": 37.32,
    "days_since_ath": 210
  },
  "PKR": {
    "drawdown_percent": 38.31,
    "days_since_ath": 210
  },
  "KWD": {
    "drawdown_percent": 37.05,
    "days_since_ath": 210
  },
  "EGP": {
    "drawdown_percent": 30.95,
    "days_since_ath": 293
  },
  "JMD": {
    "drawdown_percent": 38.64,
    "days_since_ath": 210
  },
  "XOF": {
    "drawdown_percent": 37.36,
    "days_since_ath": 210
  },
  "BGN": {
    "drawdown_percent": 37.37,
    "days_since_ath": 210
  },
  "CNY": {
    "drawdown_percent": 39.93,
    "days_since_ath": 210
  },
  "COP": {
    "drawdown_percent": 42.82,
    "days_since_ath": 265
  },
  "IDR": {
    "drawdown_percent": 34.54,
    "days_since_ath": 210
  },
  "MGA": {
    "drawdown_percent": 41.73,
    "days_since_ath": 210
  },
  "XCD": {
    "drawdown_percent": 37.45,
    "days_since_ath": 210
  },
  "MMK": {
    "drawdown_percent": 53.3,
    "days_since_ath": 467
  },
  "TMT": {
    "drawdown_percent": 37.46,
    "days_since_ath": 210
  },
  "RWF": {
    "drawdown_percent": 36.95,
    "days_since_ath": 210
  },
  "GYD": {
    "drawdown_percent": 37.47,
    "days_since_ath": 210
  },
  "BWP": {
    "drawdown_percent": 38.51,
    "days_since_ath": 210
  },
  "BDT": {
    "drawdown_percent": 36.88,
    "days_since_ath": 210
  },
  "TZS": {
    "drawdown_percent": 35.88,
    "days_since_ath": 293
  },
  "ZAR": {
    "drawdown_percent": 40.61,
    "days_since_ath": 293
  },
  "MKD": {
    "drawdown_percent": 37.28,
    "days_since_ath": 210
  },
  "AUD": {
    "drawdown_percent": 42.57,
    "days_since_ath": 210
  },
  "RON": {
    "drawdown_percent": 36.16,
    "days_since_ath": 210
  },
  "PLN": {
    "drawdown_percent": 37.41,
    "days_since_ath": 210
  },
  "BZD": {
    "drawdown_percent": 37.45,
    "days_since_ath": 210
  },
  "MVR": {
    "drawdown_percent": 37.32,
    "days_since_ath": 210
  },
  "UGX": {
    "drawdown_percent": 33.47,
    "days_since_ath": 293
  },
  "IQD": {
    "drawdown_percent": 37.4,
    "days_since_ath": 210
  },
  "UZS": {
    "drawdown_percent": 39.92,
    "days_since_ath": 293
  },
  "BMD": {
    "drawdown_percent": 37.45,
    "days_since_ath": 210
  },
  "ANG": {
    "drawdown_percent": 37.45,
    "days_since_ath": 210
  },
  "UAH": {
    "drawdown_percent": 33.26,
    "days_since_ath": 210
  },
  "ZMW": {
    "drawdown_percent": 51.42,
    "days_since_ath": 467
  },
  "INR": {
    "drawdown_percent": 33.07,
    "days_since_ath": 210
  },
  "SGD": {
    "drawdown_percent": 38.23,
    "days_since_ath": 210
  },
  "CHF": {
    "drawdown_percent": 38.77,
    "days_since_ath": 467
  },
  "MRU": {
    "drawdown_percent": 37.51,
    "days_since_ath": 210
  },
  "MZN": {
    "drawdown_percent": 37.48,
    "days_since_ath": 210
  },
  "GTQ": {
    "drawdown_percent": 37.51,
    "days_since_ath": 210
  },
  "GHS": {
    "drawdown_percent": 46.43,
    "days_since_ath": 467
  },
  "MDL": {
    "drawdown_percent": 35.39,
    "days_since_ath": 210
  }
}