{
  "NIO": {
    "drawdown_percent": 35.5,
    "days_since_ath": 220
  },
  "HTG": {
    "drawdown_percent": 35.49,
    "days_since_ath": 220
  },
  "THB": {
    "drawdown_percent": 35.53,
    "days_since_ath": 220
  },
  "LAK": {
    "drawdown_percent": 35.02,
    "days_since_ath": 220
  },
  "CRC": {
    "drawdown_percent": 41.31,
    "days_since_ath": 220
  },
  "BYN": {
    "drawdown_percent": 45.92,
    "days_since_ath": 219
  },
  "CAD": {
    "drawdown_percent": 36.67,
    "days_since_ath": 220
  },
  "ILS": {
    "drawdown_percent": 43.86,
    "days_since_ath": 275
  },
  "KHR": {
    "drawdown_percent": 35.15,
    "days_since_ath": 220
  },
  "HNL": {
    "drawdown_percent": 34.69,
    "days_since_ath": 220
  },
  "CVE": {
    "drawdown_percent": 35.57,
    "days_since_ath": 220
  },
  "PGK": {
    "drawdown_percent": 33.61,
    "days_since_ath": 220
  },
  "GNF": {
    "drawdown_percent": 34.79,
    "days_since_ath": 220
  },
  "GMD": {
    "drawdown_percent": 34.73,
    "days_since_ath": 220
  },
  "RUB": {
    "drawdown_percent": 47.48,
    "days_since_ath": 511
  },
  "JOD": {
    "drawdown_percent": 35.39,
    "days_since_ath": 220
  },
  "BRL": {
    "drawdown_percent": 41.84,
    "days_since_ath": 303
  },
  "MYR": {
    "drawdown_percent": 39.75,
    "days_since_ath": 220
  },
  "PYG": {
    "drawdown_percent": 48.52,
    "days_since_ath": 303
  },
  "KES": {
    "drawdown_percent": 35.42,
    "days_since_ath": 220
  },
  "LKR": {
    "drawdown_percent": 31.33,
    "days_since_ath": 220
  },
  "BIF": {
    "drawdown_percent": 34.85,
    "days_since_ath": 220
  },
  "CZK": {
    "drawdown_percent": 37.81,
    "days_since_ath": 477
  },
  "KZT": {
    "drawdown_percent": 45.32,
    "days_since_ath": 220
  },
  "AED": {
    "drawdown_percent": 35.38,
    "days_since_ath": 220
  },
  "AWG": {
    "drawdown_percent": 35.38,
    "days_since_ath": 220
  },
  "ARS": {
    "drawdown_percent": 36.53,
    "days_since_ath": 220
  },
  "TND": {
    "drawdown_percent": 36.12,
    "days_since_ath": 220
  },
  "EUR": {
    "drawdown_percent": 35.54,
    "days_since_ath": 220
  },
  "ISK": {
    "drawdown_percent": 35.85,
    "days_since_ath": 477
  },
  "YER": {
    "drawdown_percent": 35.65,
    "days_since_ath": 220
  },
  "SZL": {
    "drawdown_percent": 39.46,
    "days_since_ath": 303
  },
  "TRY": {
    "drawdown_percent": 29.66,
    "days_since_ath": 220
  },
  "SAR": {
    "drawdown_percent": 35.38,
    "days_since_ath": 220
  },
  "LSL": {
    "drawdown_percent": 39.46,
    "days_since_ath": 303
  },
  "JPY": {
    "drawdown_percent": 31.9,
    "days_since_ath": 216
  },
  "LRD": {
    "drawdown_percent": 39.8,
    "days_since_ath": 275
  },
  "SEK": {
    "drawdown_percent": 38.99,
    "days_since_ath": 477
  },
  "FJD": {
    "drawdown_percent": 37.42,
    "days_since_ath": 220
  },
  "KMF": {
    "drawdown_percent": 35.57,
    "days_since_ath": 220
  },
  "KYD": {
    "drawdown_percent": 35.38,
    "days_since_ath": 220
  },
  "RSD": {
    "drawdown_percent": 35.47,
    "days_since_ath": 220
  },
  "UYU": {
    "drawdown_percent": 35.46,
    "days_since_ath": 220
  },
  "HUF": {
    "drawdown_percent": 44.35,
    "days_since_ath": 477
  },
  "DZD": {
    "drawdown_percent": 34.17,
    "days_since_ath": 220
  },
  "BHD": {
    "drawdown_percent": 35.38,
    "days_since_ath": 220
  },
  "MAD": {
    "drawdown_percent": 35.39,
    "days_since_ath": 220
  },
  "NPR": {
    "drawdown_percent": 30.59,
    "days_since_ath": 220
  },
  "DKK": {
    "drawdown_percent": 35.56,
    "days_since_ath": 220
  },
  "ALL": {
    "drawdown_percent": 36.55,
    "days_since_ath": 220
  },
  "TTD": {
    "drawdown_percent": 35.52,
    "days_since_ath": 220
  },
  "MXN": {
    "drawdown_percent": 39.59,
    "days_since_ath": 220
  },
  "BND": {
    "drawdown_percent": 36.39,
    "days_since_ath": 220
  },
  "SCR": {
    "drawdown_percent": 36.04,
    "days_since_ath": 220
  },
  "XPF": {
    "drawdown_percent": 35.57,
    "days_since_ath": 220
  },
  "KRW": {
    "drawdown_percent": 32.29,
    "days_since_ath": 220
  },
  "AFN": {
    "drawdown_percent": 39.19,
    "days_since_ath": 303
  },
  "IRR": {
    "drawdown_percent": 3.61,
    "days_since_ath": 4
  },
  "OMR": {
    "drawdown_percent": 35.39,
    "days_since_ath": 220
  },
  "SOS": {
    "drawdown_percent": 35.46,
    "days_since_ath": 220
  },
  "GBP": {
    "drawdown_percent": 36.02,
    "days_since_ath": 220
  },
  "CDF": {
    "drawdown_percent": 48.79,
    "days_since_ath": 303
  },
  "PHP": {
    "drawdown_percent": 31.97,
    "days_since_ath": 220
  },
  "NGN": {
    "drawdown_percent": 41.49,
    "days_since_ath": 272
  },
  "NOK": {
    "drawdown_percent": 40.91,
    "days_since_ath": 275
  },
  "CLP": {
    "drawdown_percent": 40.08,
    "days_since_ath": 220
  },
  "USD": {
    "drawdown_percent": 35.38,
    "days_since_ath": 220
  },
  "BSD": {
    "drawdown_percent": 35.38,
    "days_since_ath": 220
  },
  "VES": {
    "drawdown_percent": 100.0,
    "days_since_ath": 6
  },
  "XAF": {
    "drawdown_percent": 35.57,
    "days_since_ath": 220
  },
  "LBP": {
    "drawdown_percent": 35.38,
    "days_since_ath": 220
  },
  "CUP": {
    "drawdown_percent": 35.38,
    "days_since_ath": 220
  },
  "DOP": {
    "drawdown_percent": 38.68,
    "days_since_ath": 220
  },
  "PAB": {
    "drawdown_percent": 35.38,
    "days_since_ath": 220
  },
  "MUR": {
    "drawdown_percent": 33.65,
    "days_since_ath": 220
  },
  "HKD": {
    "drawdown_percent": 34.99,
    "days_since_ath": 220
  },
  "LYD": {
    "drawdown_percent": 24.44,
    "days_since_ath": 220
  },
  "QAR": {
    "drawdown_percent": 35.38,
    "days_since_ath": 220
  },
  "VND": {
    "drawdown_percent": 35.59,
    "days_since_ath": 220
  },
  "DJF": {
    "drawdown_percent": 35.38,
    "days_since_ath": 220
  },
  "SDG": {
    "drawdown_percent": 44.81,
    "days_since_ath": 272
  },
  "MWK": {
    "drawdown_percent": 35.47,
    "days_since_ath": 220
  },
  "TWD": {
    "drawdown_percent": 33.35,
    "days_since_ath": 220
  },
  "MOP": {
    "drawdown_percent": 34.99,
    "days_since_ath": 220
  },
  "NZD": {
    "drawdown_percent": 36.79,
    "days_since_ath": 220
  },
  "NAD": {
    "drawdown_percent": 39.46,
    "days_since_ath": 303
  },
  "PEN": {
    "drawdown_percent": 36.19,
    "days_since_ath": 303
  },
  "ETB": {
    "drawdown_percent": 30.07,
    "days_since_ath": 219
  },
  "BBD": {
    "drawdown_percent": 35.38,
    "days_since_ath": 220
  },
  "BOB": {
    "drawdown_percent": 35.64,
    "days_since_ath": 220
  },
  "PKR": {
    "drawdown_percent": 36.41,
    "days_since_ath": 220
  },
  "KWD": {
    "drawdown_percent": 35.0,
    "days_since_ath": 220
  },
  "EGP": {
    "drawdown_percent": 29.56,
    "days_since_ath": 303
  },
  "JMD": {
    "drawdown_percent": 36.49,
    "days_since_ath": 220
  },
  "XOF": {
    "drawdown_percent": 35.57,
    "days_since_ath": 220
  },
  "BGN": {
    "drawdown_percent": 35.58,
    "days_since_ath": 220
  },
  "CNY": {
    "drawdown_percent": 38.28,
    "days_since_ath": 220
  },
  "COP": {
    "drawdown_percent": 39.15,
    "days_since_ath": 275
  },
  "IDR": {
    "drawdown_percent": 31.98,
    "days_since_ath": 220
  },
  "MGA": {
    "drawdown_percent": 39.23,
    "days_since_ath": 220
  },
  "XCD": {
    "drawdown_percent": 35.38,
    "days_since_ath": 220
  },
  "MMK": {
    "drawdown_percent": 51.97,
    "days_since_ath": 477
  },
  "TMT": {
    "drawdown_percent": 35.39,
    "days_since_ath": 220
  },
  "RWF": {
    "drawdown_percent": 34.75,
    "days_since_ath": 220
  },
  "GYD": {
    "drawdown_percent": 35.43,
    "days_since_ath": 220
  },
  "BWP": {
    "drawdown_percent": 37.12,
    "days_since_ath": 220
  },
  "BDT": {
    "drawdown_percent": 34.77,
    "days_since_ath": 220
  },
  "TZS": {
    "drawdown_percent": 34.19,
    "days_since_ath": 303
  },
  "ZAR": {
    "drawdown_percent": 39.46,
    "days_since_ath": 303
  },
  "MKD": {
    "drawdown_percent": 35.49,
    "days_since_ath": 220
  },
  "AUD": {
    "drawdown_percent": 41.11,
    "days_since_ath": 220
  },
  "RON": {
    "drawdown_percent": 33.99,
    "days_since_ath": 220
  },
  "PLN": {
    "drawdown_percent": 35.86,
    "days_since_ath": 220
  },
  "BZD": {
    "drawdown_percent": 35.38,
    "days_since_ath": 220
  },
  "MVR": {
    "drawdown_percent": 35.43,
    "days_since_ath": 220
  },
  "UGX": {
    "drawdown_percent": 31.31,
    "days_since_ath": 303
  },
  "IQD": {
    "drawdown_percent": 35.42,
    "days_since_ath": 220
  },
  "UZS": {
    "drawdown_percent": 36.68,
    "days_since_ath": 303
  },
  "BMD": {
    "drawdown_percent": 35.38,
    "days_since_ath": 220
  },
  "ANG": {
    "drawdown_percent": 35.38,
    "days_since_ath": 220
  },
  "UAH": {
    "drawdown_percent": 31.18,
    "days_since_ath": 220
  },
  "ZMW": {
    "drawdown_percent": 49.24,
    "days_since_ath": 477
  },
  "INR": {
    "drawdown_percent": 30.59,
    "days_since_ath": 220
  },
  "SGD": {
    "drawdown_percent": 36.38,
    "days_since_ath": 220
  },
  "CHF": {
    "drawdown_percent": 37.08,
    "days_since_ath": 477
  },
  "MRU": {
    "drawdown_percent": 35.45,
    "days_since_ath": 220
  },
  "MZN": {
    "drawdown_percent": 35.56,
    "days_since_ath": 220
  },
  "GTQ": {
    "drawdown_percent": 35.77,
    "days_since_ath": 220
  },
  "GHS": {
    "drawdown_percent": 44.27,
    "days_since_ath": 477
  },
  "MDL": {
    "drawdown_percent": 33.64,
    "days_since_ath": 220
  }
}