{
  "NIO": {
    "drawdown_percent": 47.33,
    "days_since_ath": 291
  },
  "HTG": {
    "drawdown_percent": 47.47,
    "days_since_ath": 291
  },
  "THB": {
    "drawdown_percent": 45.09,
    "days_since_ath": 291
  },
  "LAK": {
    "drawdown_percent": 45.61,
    "days_since_ath": 291
  },
  "CRC": {
    "drawdown_percent": 52.61,
    "days_since_ath": 291
  },
  "BYN": {
    "drawdown_percent": 54.43,
    "days_since_ath": 290
  },
  "CAD": {
    "drawdown_percent": 46.85,
    "days_since_ath": 291
  },
  "ILS": {
    "drawdown_percent": 51.82,
    "days_since_ath": 346
  },
  "KHR": {
    "drawdown_percent": 46.96,
    "days_since_ath": 291
  },
  "HNL": {
    "drawdown_percent": 46.3,
    "days_since_ath": 291
  },
  "CVE": {
    "drawdown_percent": 45.85,
    "days_since_ath": 291
  },
  "PGK": {
    "drawdown_percent": 44.41,
    "days_since_ath": 291
  },
  "GNF": {
    "drawdown_percent": 46.76,
    "days_since_ath": 291
  },
  "GMD": {
    "drawdown_percent": 46.65,
    "days_since_ath": 291
  },
  "RUB": {
    "drawdown_percent": 54.5,
    "days_since_ath": 582
  },
  "JOD": {
    "drawdown_percent": 47.37,
    "days_since_ath": 291
  },
  "BRL": {
    "drawdown_percent": 50.97,
    "days_since_ath": 374
  },
  "MYR": {
    "drawdown_percent": 48.87,
    "days_since_ath": 291
  },
  "PYG": {
    "drawdown_percent": 58.34,
    "days_since_ath": 374
  },
  "KES": {
    "drawdown_percent": 47.32,
    "days_since_ath": 291
  },
  "LKR": {
    "drawdown_percent": 41.48,
    "days_since_ath": 291
  },
  "BIF": {
    "drawdown_percent": 46.77,
    "days_since_ath": 291
  },
  "CZK": {
    "drawdown_percent": 48.06,
    "days_since_ath": 548
  },
  "KZT": {
    "drawdown_percent": 55.05,
    "days_since_ath": 291
  },
  "AED": {
    "drawdown_percent": 47.37,
    "days_since_ath": 291
  },
  "AWG": {
    "drawdown_percent": 47.37,
    "days_since_ath": 291
  },
  "ARS": {
    "drawdown_percent": 45.3,
    "days_since_ath": 291
  },
  "TND": {
    "drawdown_percent": 46.58,
    "days_since_ath": 291
  },
  "EUR": {
    "drawdown_percent": 45.85,
    "days_since_ath": 291
  },
  "ISK": {
    "drawdown_percent": 46.34,
    "days_since_ath": 548
  },
  "YER": {
    "drawdown_percent": 47.56,
    "days_since_ath": 291
  },
  "SZL": {
    "drawdown_percent": 50.73,
    "days_since_ath": 374
  },
  "TRY": {
    "drawdown_percent": 40.36,
    "days_since_ath": 291
  },
  "SAR": {
    "drawdown_percent": 47.37,
    "days_since_ath": 291
  },
  "LSL": {
    "drawdown_percent": 50.73,
    "days_since_ath": 374
  },
  "JPY": {
    "drawdown_percent": 42.44,
    "days_since_ath": 287
  },
  "LRD": {
    "drawdown_percent": 51.45,
    "days_since_ath": 346
  },
  "SEK": {
    "drawdown_percent": 47.73,
    "days_since_ath": 548
  },
  "FJD": {
    "drawdown_percent": 47.71,
    "days_since_ath": 291
  },
  "KMF": {
    "drawdown_percent": 45.85,
    "days_since_ath": 291
  },
  "KYD": {
    "drawdown_percent": 47.37,
    "days_since_ath": 291
  },
  "RSD": {
    "drawdown_percent": 45.75,
    "days_since_ath": 291
  },
  "UYU": {
    "drawdown_percent": 46.98,
    "days_since_ath": 291
  },
  "HUF": {
    "drawdown_percent": 52.16,
    "days_since_ath": 548
  },
  "DZD": {
    "drawdown_percent": 45.94,
    "days_since_ath": 291
  },
  "BHD": {
    "drawdown_percent": 47.37,
    "days_since_ath": 291
  },
  "MAD": {
    "drawdown_percent": 45.78,
    "days_since_ath": 291
  },
  "NPR": {
    "drawdown_percent": 42.73,
    "days_since_ath": 291
  },
  "DKK": {
    "drawdown_percent": 45.84,
    "days_since_ath": 291
  },
  "ALL": {
    "drawdown_percent": 47.61,
    "days_since_ath": 291
  },
  "TTD": {
    "drawdown_percent": 47.25,
    "days_since_ath": 291
  },
  "MXN": {
    "drawdown_percent": 50.2,
    "days_since_ath": 291
  },
  "BND": {
    "drawdown_percent": 47.28,
    "days_since_ath": 291
  },
  "SCR": {
    "drawdown_percent": 51.1,
    "days_since_ath": 291
  },
  "XPF": {
    "drawdown_percent": 45.85,
    "days_since_ath": 291
  },
  "KRW": {
    "drawdown_percent": 44.65,
    "days_since_ath": 291
  },
  "AFN": {
    "drawdown_percent": 48.54,
    "days_since_ath": 374
  },
  "IRR": {
    "drawdown_percent": 15.93,
    "days_since_ath": 75
  },
  "OMR": {
    "drawdown_percent": 47.37,
    "days_since_ath": 291
  },
  "SOS": {
    "drawdown_percent": 47.43,
    "days_since_ath": 291
  },
  "GBP": {
    "drawdown_percent": 46.98,
    "days_since_ath": 291
  },
  "CDF": {
    "drawdown_percent": 57.61,
    "days_since_ath": 374
  },
  "PHP": {
    "drawdown_percent": 43.87,
    "days_since_ath": 291
  },
  "NGN": {
    "drawdown_percent": 51.8,
    "days_since_ath": 343
  },
  "NOK": {
    "drawdown_percent": 49.74,
    "days_since_ath": 346
  },
  "CLP": {
    "drawdown_percent": 48.83,
    "days_since_ath": 291
  },
  "USD": {
    "drawdown_percent": 47.37,
    "days_since_ath": 291
  },
  "BSD": {
    "drawdown_percent": 47.37,
    "days_since_ath": 291
  },
  "VES": {
    "drawdown_percent": 0.19,
    "days_since_ath": 1
  },
  "XAF": {
    "drawdown_percent": 45.85,
    "days_since_ath": 291
  },
  "LBP": {
    "drawdown_percent": 47.37,
    "days_since_ath": 291
  },
  "CUP": {
    "drawdown_percent": 47.37,
    "days_since_ath": 291
  },
  "DOP": {
    "drawdown_percent": 50.81,
    "days_since_ath": 291
  },
  "PAB": {
    "drawdown_percent": 47.37,
    "days_since_ath": 291
  },
  "MUR": {
    "drawdown_percent": 45.33,
    "days_since_ath": 291
  },
  "HKD": {
    "drawdown_percent": 46.97,
    "days_since_ath": 291
  },
  "LYD": {
    "drawdown_percent": 37.6,
    "days_since_ath": 291
  },
  "QAR": {
    "drawdown_percent": 47.37,
    "days_since_ath": 291
  },
  "VND": {
    "drawdown_percent": 47.4,
    "days_since_ath": 291
  },
  "DJF": {
    "drawdown_percent": 47.37,
    "days_since_ath": 291
  },
  "SDG": {
    "drawdown_percent": 46.15,
    "days_since_ath": 343
  },
  "MWK": {
    "drawdown_percent": 47.46,
    "days_since_ath": 291
  },
  "TWD": {
    "drawdown_percent": 43.92,
    "days_since_ath": 291
  },
  "MOP": {
    "drawdown_percent": 46.98,
    "days_since_ath": 291
  },
  "NZD": {
    "drawdown_percent": 47.21,
    "days_since_ath": 291
  },
  "NAD": {
    "drawdown_percent": 50.73,
    "days_since_ath": 374
  },
  "PEN": {
    "drawdown_percent": 48.5,
    "days_since_ath": 374
  },
  "ETB": {
    "drawdown_percent": 41.34,
    "days_since_ath": 290
  },
  "BBD": {
    "drawdown_percent": 47.37,
    "days_since_ath": 291
  },
  "BOB": {
    "drawdown_percent": 17.56,
    "days_since_ath": 291
  },
  "PKR": {
    "drawdown_percent": 48.39,
    "days_since_ath": 291
  },
  "KWD": {
    "drawdown_percent": 46.74,
    "days_since_ath": 291
  },
  "EGP": {
    "drawdown_percent": 44.2,
    "days_since_ath": 374
  },
  "JMD": {
    "drawdown_percent": 47.94,
    "days_since_ath": 291
  },
  "XOF": {
    "drawdown_percent": 45.85,
    "days_since_ath": 291
  },
  "BGN": {
    "drawdown_percent": 45.85,
    "days_since_ath": 291
  },
  "CNY": {
    "drawdown_percent": 49.93,
    "days_since_ath": 291
  },
  "COP": {
    "drawdown_percent": 57.29,
    "days_since_ath": 346
  },
  "IDR": {
    "drawdown_percent": 43.15,
    "days_since_ath": 291
  },
  "MGA": {
    "drawdown_percent": 49.36,
    "days_since_ath": 291
  },
  "XCD": {
    "drawdown_percent": 47.37,
    "days_since_ath": 291
  },
  "MMK": {
    "drawdown_percent": 60.84,
    "days_since_ath": 548
  },
  "TMT": {
    "drawdown_percent": 47.36,
    "days_since_ath": 291
  },
  "RWF": {
    "drawdown_percent": 46.63,
    "days_since_ath": 291
  },
  "GYD": {
    "drawdown_percent": 47.39,
    "days_since_ath": 291
  },
  "BWP": {
    "drawdown_percent": 48.21,
    "days_since_ath": 291
  },
  "BDT": {
    "drawdown_percent": 46.62,
    "days_since_ath": 291
  },
  "TZS": {
    "drawdown_percent": 45.71,
    "days_since_ath": 374
  },
  "ZAR": {
    "drawdown_percent": 50.74,
    "days_since_ath": 374
  },
  "MKD": {
    "drawdown_percent": 45.99,
    "days_since_ath": 291
  },
  "AUD": {
    "drawdown_percent": 50.3,
    "days_since_ath": 291
  },
  "RON": {
    "drawdown_percent": 44.27,
    "days_since_ath": 291
  },
  "PLN": {
    "drawdown_percent": 44.92,
    "days_since_ath": 291
  },
  "BZD": {
    "drawdown_percent": 47.37,
    "days_since_ath": 291
  },
  "MVR": {
    "drawdown_percent": 47.32,
    "days_since_ath": 291
  },
  "UGX": {
    "drawdown_percent": 44.25,
    "days_since_ath": 374
  },
  "IQD": {
    "drawdown_percent": 47.35,
    "days_since_ath": 291
  },
  "UZS": {
    "drawdown_percent": 49.16,
    "days_since_ath": 374
  },
  "BMD": {
    "drawdown_percent": 47.37,
    "days_since_ath": 291
  },
  "ANG": {
    "drawdown_percent": 47.37,
    "days_since_ath": 291
  },
  "UAH": {
    "drawdown_percent": 42.87,
    "days_since_ath": 291
  },
  "ZMW": {
    "drawdown_percent": 60.16,
    "days_since_ath": 548
  },
  "INR": {
    "drawdown_percent": 42.74,
    "days_since_ath": 291
  },
  "SGD": {
    "drawdown_percent": 47.28,
    "days_since_ath": 291
  },
  "CHF": {
    "drawdown_percent": 46.4,
    "days_since_ath": 548
  },
  "MRU": {
    "drawdown_percent": 47.25,
    "days_since_ath": 291
  },
  "MZN": {
    "drawdown_percent": 47.44,
    "days_since_ath": 291
  },
  "GTQ": {
    "drawdown_percent": 47.62,
    "days_since_ath": 291
  },
  "GHS": {
    "drawdown_percent": 53.37,
    "days_since_ath": 548
  },
  "MDL": {
    "drawdown_percent": 44.58,
    "days_since_ath": 291
  }
}