{
  "NIO": {
    "drawdown_percent": 8.03,
    "days_since_ath": 71
  },
  "HTG": {
    "drawdown_percent": 8.18,
    "days_since_ath": 71
  },
  "THB": {
    "drawdown_percent": 9.84,
    "days_since_ath": 71
  },
  "LAK": {
    "drawdown_percent": 8.26,
    "days_since_ath": 71
  },
  "CRC": {
    "drawdown_percent": 8.29,
    "days_since_ath": 43
  },
  "BYN": {
    "drawdown_percent": 8.99,
    "days_since_ath": 43
  },
  "CAD": {
    "drawdown_percent": 7.62,
    "days_since_ath": 43
  },
  "ILS": {
    "drawdown_percent": 9.91,
    "days_since_ath": 43
  },
  "KHR": {
    "drawdown_percent": 8.17,
    "days_since_ath": 43
  },
  "HNL": {
    "drawdown_percent": 8.04,
    "days_since_ath": 43
  },
  "CVE": {
    "drawdown_percent": 10.13,
    "days_since_ath": 245
  },
  "PGK": {
    "drawdown_percent": 8.06,
    "days_since_ath": 40
  },
  "GNF": {
    "drawdown_percent": 8.28,
    "days_since_ath": 43
  },
  "GMD": {
    "drawdown_percent": 7.28,
    "days_since_ath": 43
  },
  "RUB": {
    "drawdown_percent": 17.18,
    "days_since_ath": 279
  },
  "JOD": {
    "drawdown_percent": 8.05,
    "days_since_ath": 71
  },
  "BRL": {
    "drawdown_percent": 11.71,
    "days_since_ath": 71
  },
  "MYR": {
    "drawdown_percent": 9.09,
    "days_since_ath": 71
  },
  "PYG": {
    "drawdown_percent": 16.43,
    "days_since_ath": 71
  },
  "KES": {
    "drawdown_percent": 8.11,
    "days_since_ath": 71
  },
  "LKR": {
    "drawdown_percent": 7.59,
    "days_since_ath": 71
  },
  "BIF": {
    "drawdown_percent": 8.48,
    "days_since_ath": 43
  },
  "CZK": {
    "drawdown_percent": 13.78,
    "days_since_ath": 245
  },
  "KZT": {
    "drawdown_percent": 7.57,
    "days_since_ath": 43
  },
  "AED": {
    "drawdown_percent": 8.05,
    "days_since_ath": 71
  },
  "AWG": {
    "drawdown_percent": 8.05,
    "days_since_ath": 71
  },
  "ARS": {
    "drawdown_percent": 7.02,
    "days_since_ath": 5
  },
  "TND": {
    "drawdown_percent": 8.05,
    "days_since_ath": 71
  },
  "EUR": {
    "drawdown_percent": 10.23,
    "days_since_ath": 245
  },
  "ISK": {
    "drawdown_percent": 11.34,
    "days_since_ath": 245
  },
  "YER": {
    "drawdown_percent": 8.84,
    "days_since_ath": 71
  },
  "SZL": {
    "drawdown_percent": 11.07,
    "days_since_ath": 71
  },
  "TRY": {
    "drawdown_percent": 6.54,
    "days_since_ath": 43
  },
  "SAR": {
    "drawdown_percent": 8.05,
    "days_since_ath": 71
  },
  "LSL": {
    "drawdown_percent": 11.07,
    "days_since_ath": 71
  },
  "JPY": {
    "drawdown_percent": 7.94,
    "days_since_ath": 43
  },
  "LRD": {
    "drawdown_percent": 18.18,
    "days_since_ath": 43
  },
  "SEK": {
    "drawdown_percent": 13.76,
    "days_since_ath": 245
  },
  "FJD": {
    "drawdown_percent": 8.06,
    "days_since_ath": 43
  },
  "KMF": {
    "drawdown_percent": 10.25,
    "days_since_ath": 245
  },
  "KYD": {
    "drawdown_percent": 8.05,
    "days_since_ath": 71
  },
  "RSD": {
    "drawdown_percent": 9.77,
    "days_since_ath": 245
  },
  "UYU": {
    "drawdown_percent": 9.54,
    "days_since_ath": 71
  },
  "HUF": {
    "drawdown_percent": 15.32,
    "days_since_ath": 245
  },
  "DZD": {
    "drawdown_percent": 8.34,
    "days_since_ath": 43
  },
  "BHD": {
    "drawdown_percent": 8.05,
    "days_since_ath": 71
  },
  "MAD": {
    "drawdown_percent": 8.17,
    "days_since_ath": 43
  },
  "NPR": {
    "drawdown_percent": 7.29,
    "days_since_ath": 43
  },
  "DKK": {
    "drawdown_percent": 10.25,
    "days_since_ath": 245
  },
  "ALL": {
    "drawdown_percent": 9.48,
    "days_since_ath": 71
  },
  "TTD": {
    "drawdown_percent": 8.11,
    "days_since_ath": 71
  },
  "MXN": {
    "drawdown_percent": 9.51,
    "days_since_ath": 71
  },
  "BND": {
    "drawdown_percent": 8.21,
    "days_since_ath": 43
  },
  "SCR": {
    "drawdown_percent": 7.8,
    "days_since_ath": 43
  },
  "XPF": {
    "drawdown_percent": 10.07,
    "days_since_ath": 245
  },
  "KRW": {
    "drawdown_percent": 7.92,
    "days_since_ath": 43
  },
  "AFN": {
    "drawdown_percent": 9.1,
    "days_since_ath": 71
  },
  "IRR": {
    "drawdown_percent": 9.53,
    "days_since_ath": 43
  },
  "OMR": {
    "drawdown_percent": 8.05,
    "days_since_ath": 71
  },
  "SOS": {
    "drawdown_percent": 8.18,
    "days_since_ath": 43
  },
  "GBP": {
    "drawdown_percent": 8.47,
    "days_since_ath": 43
  },
  "CDF": {
    "drawdown_percent": 9.85,
    "days_since_ath": 71
  },
  "PHP": {
    "drawdown_percent": 7.9,
    "days_since_ath": 43
  },
  "NGN": {
    "drawdown_percent": 10.39,
    "days_since_ath": 40
  },
  "NOK": {
    "drawdown_percent": 11.16,
    "days_since_ath": 43
  },
  "CLP": {
    "drawdown_percent": 9.32,
    "days_since_ath": 43
  },
  "USD": {
    "drawdown_percent": 8.05,
    "days_since_ath": 71
  },
  "BSD": {
    "drawdown_percent": 8.05,
    "days_since_ath": 71
  },
  "VES": {
    "drawdown_percent": 2.07,
    "days_since_ath": 4
  },
  "XAF": {
    "drawdown_percent": 10.13,
    "days_since_ath": 245
  },
  "LBP": {
    "drawdown_percent": 8.05,
    "days_since_ath": 71
  },
  "CUP": {
    "drawdown_percent": 8.05,
    "days_since_ath": 71
  },
  "DOP": {
    "drawdown_percent": 6.65,
    "days_since_ath": 40
  },
  "PAB": {
    "drawdown_percent": 8.05,
    "days_since_ath": 71
  },
  "MUR": {
    "drawdown_percent": 7.78,
    "days_since_ath": 43
  },
  "HKD": {
    "drawdown_percent": 8.98,
    "days_since_ath": 71
  },
  "LYD": {
    "drawdown_percent": 8.61,
    "days_since_ath": 40
  },
  "QAR": {
    "drawdown_percent": 8.05,
    "days_since_ath": 71
  },
  "VND": {
    "drawdown_percent": 7.58,
    "days_since_ath": 43
  },
  "DJF": {
    "drawdown_percent": 8.05,
    "days_since_ath": 71
  },
  "SDG": {
    "drawdown_percent": 23.19,
    "days_since_ath": 40
  },
  "MWK": {
    "drawdown_percent": 7.75,
    "days_since_ath": 43
  },
  "TWD": {
    "drawdown_percent": 6.98,
    "days_since_ath": 40
  },
  "MOP": {
    "drawdown_percent": 8.98,
    "days_since_ath": 71
  },
  "NZD": {
    "drawdown_percent": 6.68,
    "days_since_ath": 43
  },
  "NAD": {
    "drawdown_percent": 11.07,
    "days_since_ath": 71
  },
  "PEN": {
    "drawdown_percent": 9.44,
    "days_since_ath": 71
  },
  "ETB": {
    "drawdown_percent": 5.68,
    "days_since_ath": 40
  },
  "BBD": {
    "drawdown_percent": 8.05,
    "days_since_ath": 71
  },
  "BOB": {
    "drawdown_percent": 8.27,
    "days_since_ath": 71
  },
  "PKR": {
    "drawdown_percent": 8.23,
    "days_since_ath": 71
  },
  "KWD": {
    "drawdown_percent": 8.09,
    "days_since_ath": 71
  },
  "EGP": {
    "drawdown_percent": 10.45,
    "days_since_ath": 71
  },
  "JMD": {
    "drawdown_percent": 8.0,
    "days_since_ath": 71
  },
  "XOF": {
    "drawdown_percent": 10.13,
    "days_since_ath": 245
  },
  "BGN": {
    "drawdown_percent": 9.84,
    "days_since_ath": 245
  },
  "CNY": {
    "drawdown_percent": 8.95,
    "days_since_ath": 43
  },
  "COP": {
    "drawdown_percent": 12.2,
    "days_since_ath": 43
  },
  "IDR": {
    "drawdown_percent": 6.12,
    "days_since_ath": 43
  },
  "MGA": {
    "drawdown_percent": 7.31,
    "days_since_ath": 43
  },
  "XCD": {
    "drawdown_percent": 8.05,
    "days_since_ath": 71
  },
  "MMK": {
    "drawdown_percent": 33.01,
    "days_since_ath": 245
  },
  "TMT": {
    "drawdown_percent": 8.04,
    "days_since_ath": 71
  },
  "RWF": {
    "drawdown_percent": 7.61,
    "days_since_ath": 40
  },
  "GYD": {
    "drawdown_percent": 8.06,
    "days_since_ath": 71
  },
  "BWP": {
    "drawdown_percent": 6.13,
    "days_since_ath": 54
  },
  "BDT": {
    "drawdown_percent": 7.8,
    "days_since_ath": 43
  },
  "TZS": {
    "drawdown_percent": 13.43,
    "days_since_ath": 71
  },
  "ZAR": {
    "drawdown_percent": 11.08,
    "days_since_ath": 71
  },
  "MKD": {
    "drawdown_percent": 8.85,
    "days_since_ath": 245
  },
  "AUD": {
    "drawdown_percent": 9.1,
    "days_since_ath": 43
  },
  "RON": {
    "drawdown_percent": 8.97,
    "days_since_ath": 43
  },
  "PLN": {
    "drawdown_percent": 10.26,
    "days_since_ath": 245
  },
  "BZD": {
    "drawdown_percent": 8.05,
    "days_since_ath": 71
  },
  "MVR": {
    "drawdown_percent": 8.09,
    "days_since_ath": 71
  },
  "UGX": {
    "drawdown_percent": 10.12,
    "days_since_ath": 71
  },
  "IQD": {
    "drawdown_percent": 8.18,
    "days_since_ath": 43
  },
  "UZS": {
    "drawdown_percent": 11.25,
    "days_since_ath": 71
  },
  "BMD": {
    "drawdown_percent": 8.05,
    "days_since_ath": 71
  },
  "ANG": {
    "drawdown_percent": 8.05,
    "days_since_ath": 71
  },
  "UAH": {
    "drawdown_percent": 8.95,
    "days_since_ath": 71
  },
  "ZMW": {
    "drawdown_percent": 12.06,
    "days_since_ath": 245
  },
  "INR": {
    "drawdown_percent": 7.29,
    "days_since_ath": 43
  },
  "SGD": {
    "drawdown_percent": 8.21,
    "days_since_ath": 43
  },
  "CHF": {
    "drawdown_percent": 10.72,
    "days_since_ath": 245
  },
  "MRU": {
    "drawdown_percent": 8.11,
    "days_since_ath": 43
  },
  "MZN": {
    "drawdown_percent": 8.24,
    "days_since_ath": 43
  },
  "GTQ": {
    "drawdown_percent": 8.35,
    "days_since_ath": 71
  },
  "GHS": {
    "drawdown_percent": 12.25,
    "days_since_ath": 245
  },
  "MDL": {
    "drawdown_percent": 9.8,
    "days_since_ath": 43
  }
}